spatialsoul/codex.py
spatialsoul/fiji.py
spatialsoul/shell.py
spatial_soul-0.1.3.dist-info/LICENSE
spatial_soul-0.1.3.dist-info/METADATA
spatial_soul-0.1.3.dist-info/WHEEL
spatial_soul-0.1.3.dist-info/top_level.txt
spatial_soul-0.1.3.dist-info/RECORD
